mpet/__init__.py
mpet/daeVariableTypes.py
mpet/data_reporting.py
mpet/exceptions.py
mpet/extern_funcs.py
mpet/geometry.py
mpet/main.py
mpet/mod_CCCVCPcycle.py
mpet/mod_cell.py
mpet/mod_electrodes.py
mpet/mod_interface.py
mpet/ports.py
mpet/props_am.py
mpet/sim.py
mpet/utils.py
mpet/version.py
mpet/config/__init__.py
mpet/config/configuration.py
mpet/config/constants.py
mpet/config/derived_values.py
mpet/config/parameterset.py
mpet/config/schemas.py
mpet/electrode/diffusion/NMC532_Colclasure20.py
mpet/electrode/diffusion/__init__.py
mpet/electrode/diffusion/constant.py
mpet/electrode/diffusion/lattice.py
mpet/electrode/materials/LTO.py
mpet/electrode/materials/LiC6.py
mpet/electrode/materials/LiC6_1param.py
mpet/electrode/materials/LiC6_2step_ss.py
mpet/electrode/materials/LiC6_Colclasure_1506T.py
mpet/electrode/materials/LiC6_LIONSIMBA.py
mpet/electrode/materials/LiC6_coke_ss.py
mpet/electrode/materials/LiC6_coke_ss2.py
mpet/electrode/materials/LiC6_ss.py
mpet/electrode/materials/LiC6_ss2.py
mpet/electrode/materials/LiCoO2_LIONSIMBA.py
mpet/electrode/materials/LiFePO4.py
mpet/electrode/materials/LiMn2O4_ss.py
mpet/electrode/materials/LiMn2O4_ss2.py
mpet/electrode/materials/Li_ss.py
mpet/electrode/materials/NCA_ss1.py
mpet/electrode/materials/NCA_ss2.py
mpet/electrode/materials/NMC532_Colclasure20.py
mpet/electrode/materials/__init__.py
mpet/electrode/materials/testIS_ss.py
mpet/electrode/materials/testRS.py
mpet/electrode/materials/testRS_ps.py
mpet/electrode/materials/testRS_ss.py
mpet/electrode/reactions/BV.py
mpet/electrode/reactions/BV_Colclasure20.py
mpet/electrode/reactions/BV_NMC_Park2021.py
mpet/electrode/reactions/BV_gMod01.py
mpet/electrode/reactions/BV_mod01.py
mpet/electrode/reactions/BV_mod02.py
mpet/electrode/reactions/BV_raw.py
mpet/electrode/reactions/CIET.py
mpet/electrode/reactions/MHC.py
mpet/electrode/reactions/MHC_kfunc.py
mpet/electrode/reactions/Marcus.py
mpet/electrode/reactions/__init__.py
mpet/electrolyte/Colclasure20.py
mpet-1.0.0.dist-info/LICENSE
mpet-1.0.0.dist-info/METADATA
mpet-1.0.0.dist-info/WHEEL
mpet-1.0.0.dist-info/top_level.txt
mpet-1.0.0.dist-info/RECORD
