Metadata-Version: 2.1
Name: mpet
Version: 1.0.0
Summary: Multiphase porous electrode theory
Home-page: https://github.com/TRI-AMDD/mpet
Author: Dan Cogswell
Author-email: cogswell@mit.edu
License: MIT
Classifier: Programming Language :: Python :: 3
Requires-Python: >=3.6
License-File: LICENSE
Requires-Dist: numpy
Requires-Dist: scipy
Requires-Dist: matplotlib
Requires-Dist: pyQt5
Requires-Dist: h5py
Requires-Dist: configparser
Requires-Dist: schema
Provides-Extra: cluster_jobs
Requires-Dist: dask-jobqueue ; extra == 'cluster_jobs'
Requires-Dist: bokeh ; extra == 'cluster_jobs'
Provides-Extra: dashboard
Requires-Dist: dash ; extra == 'dashboard'
Requires-Dist: dash-bootstrap-components ; extra == 'dashboard'
Provides-Extra: doc
Requires-Dist: sphinx ; extra == 'doc'
Requires-Dist: sphinx-rtd-theme ; extra == 'doc'
Provides-Extra: test
Requires-Dist: pytest ; extra == 'test'
Requires-Dist: coverage ; extra == 'test'
Requires-Dist: coveralls ; extra == 'test'
Requires-Dist: flake8 ; extra == 'test'
